## Tasks
0. My first square
Write an empty class Square that defines a square:

File: 0-square.py
   
1. Square with size
Write a class Square that defines a square by: (based on 0-square.py)
```
guillaume@ubuntu:~/0x06$ ./1-main.py
<class '1-square.Square'>
{'_Square__size': 3}
'Square' object has no attribute 'size'
'Square' object has no attribute '__size'
guillaume@ubuntu:~/0x06$ 
```
File: 1-square.py
   
2. Size validation
Write a class Square that defines a square by: (based on 1-square.py)
```
guillaume@ubuntu:~/0x06$ ./2-main.py
<class '2-square.Square'>
{'_Square__size': 3}
<class '2-square.Square'>
{'_Square__size': 0}
'Square' object has no attribute 'size'
'Square' object has no attribute '__size'
size must be an integer
size must be >= 0
guillaume@ubuntu:~/0x06$ 
```
File: 2-square.py
   
3. Area of a square
Write a class Square that defines a square by: (based on 2-square.py)
```
guillaume@ubuntu:~/0x06$ ./3-main.py
Area: 9
'Square' object has no attribute 'size'
'Square' object has no attribute '__size'
Area: 25
guillaume@ubuntu:~/0x06$ 
```
File: 3-square.py
   
4. Access and update private attribute
Write a class Square that defines a square by: (based on 3-square.py)
```
guillaume@ubuntu:~/0x06$ ./4-main.py
Area: 7921 for size: 89
Area: 9 for size: 3
size must be an integer
guillaume@ubuntu:~/0x06$ 
```
File: 4-square.py
   
5. Printing a square
Write a class Square that defines a square by: (based on 4-square.py)
```
guillaume@ubuntu:~/0x06$ ./5-main.py
###
###
###
--
##########
##########
##########
##########
##########
##########
##########
##########
##########
##########
--

--
guillaume@ubuntu:~/0x06$ 
```
File: 5-square.py
   
6. Coordinates of a square
Write a class Square that defines a square by: (based on 5-square.py)
```
guillaume@ubuntu:~/0x06$ ./6-main.py | tr " " "_" | cat -e
###$
###$
###$
--$
$
_###$
_###$
_###$
--$
___###$
___###$
___###$
--$
guillaume@ubuntu:~/0x06$ 
```
File: 6-square.py
   
7. Singly linked list
Write a class Node that defines a node of a singly linked list by:
```
guillaume@ubuntu:~/0x06$ ./100-main.py
-4
-3
1
2
3
3
4
5
5
10
12
guillaume@ubuntu:~/0x06$ 
```
File: 100-singly_linked_list.py
   
8. Print Square instance
Write a class Square that defines a square by: (based on 6-square.py)
```
guillaume@ubuntu:~/0x06$ ./101-main.py | tr " " "_" | cat -e
#####$
#####$
#####$
#####$
#####$
--$
$
____#####$
____#####$
____#####$
____#####$
____#####$
guillaume@ubuntu:~/0x06$ 
```
File: 101-square.py
   
9. Compare 2 squares
Write a class Square that defines a square by: (based on 4-square.py)
```
guillaume@ubuntu:~/0x06$ ./102-main.py
Square 5 < Square 6
Square 5 <= Square 6
Square 5 != Square 6
guillaume@ubuntu:~/0x06$ 
```
File: 102-square.py
   
10. ByteCode -> Python #5
Write the Python class MagicClass that does exactly the same as the following Python bytecode:
```
Disassembly of __init__:
 10           0 LOAD_CONST               1 (0)
              3 LOAD_FAST                0 (self)
              6 STORE_ATTR               0 (_MagicClass__radius)

 11           9 LOAD_GLOBAL              1 (type)
             12 LOAD_FAST                1 (radius)
             15 CALL_FUNCTION            1 (1 positional, 0 keyword pair)
             18 LOAD_GLOBAL              2 (int)
             21 COMPARE_OP               9 (is not)
             24 POP_JUMP_IF_FALSE       60
             27 LOAD_GLOBAL              1 (type)
             30 LOAD_FAST                1 (radius)
             33 CALL_FUNCTION            1 (1 positional, 0 keyword pair)
             36 LOAD_GLOBAL              3 (float)
             39 COMPARE_OP               9 (is not)
             42 POP_JUMP_IF_FALSE       60

 12          45 LOAD_GLOBAL              4 (TypeError)
             48 LOAD_CONST               2 ('radius must be a number')
             51 CALL_FUNCTION            1 (1 positional, 0 keyword pair)
             54 RAISE_VARARGS            1
             57 JUMP_FORWARD             0 (to 60)

 13     >>   60 LOAD_FAST                1 (radius)
             63 LOAD_FAST                0 (self)
             66 STORE_ATTR               0 (_MagicClass__radius)
             69 LOAD_CONST               3 (None)
             72 RETURN_VALUE

Disassembly of area:
 17           0 LOAD_FAST                0 (self)
              3 LOAD_ATTR                0 (_MagicClass__radius)
              6 LOAD_CONST               1 (2)
              9 BINARY_POWER
             10 LOAD_GLOBAL              1 (math)
             13 LOAD_ATTR                2 (pi)
             16 BINARY_MULTIPLY
             17 RETURN_VALUE

Disassembly of circumference:
 21           0 LOAD_CONST               1 (2)
              3 LOAD_GLOBAL              0 (math)
              6 LOAD_ATTR                1 (pi)
              9 BINARY_MULTIPLY
             10 LOAD_FAST                0 (self)
             13 LOAD_ATTR                2 (_MagicClass__radius)
             16 BINARY_MULTIPLY
             17 RETURN_VALUE
```
File: 103-magic_class.py
